eth_keys/__init__.py
eth_keys/constants.py
eth_keys/datatypes.py
eth_keys/exceptions.py
eth_keys/main.py
eth_keys/py.typed
eth_keys/validation.py
eth_keys/backends/__init__.py
eth_keys/backends/base.py
eth_keys/backends/coincurve.py
eth_keys/backends/native/__init__.py
eth_keys/backends/native/ecdsa.py
eth_keys/backends/native/jacobian.py
eth_keys/backends/native/main.py
eth_keys/tools/__init__.py
eth_keys/tools/factories.py
eth_keys/utils/__init__.py
eth_keys/utils/address.py
eth_keys/utils/der.py
eth_keys/utils/module_loading.py
eth_keys/utils/numeric.py
eth_keys/utils/padding.py
eth_keys-0.6.0.dist-info/LICENSE
eth_keys-0.6.0.dist-info/METADATA
eth_keys-0.6.0.dist-info/WHEEL
eth_keys-0.6.0.dist-info/top_level.txt
eth_keys-0.6.0.dist-info/RECORD
