Metadata-Version: 2.1
Name: eth-keys
Version: 0.6.0
Summary: eth-keys: Common API for Ethereum key operations
Home-page: https://github.com/ethereum/eth-keys
Author: The Ethereum Foundation
Author-email: snakecharmers@ethereum.org
License: MIT
Keywords: ethereum
Classifier: Development Status :: 4 - Beta
Classifier: Intended Audience :: Developers
Classifier: License :: OSI Approved :: MIT License
Classifier: Natural Language :: English
Classifier: Programming Language :: Python :: 3
Classifier: Programming Language :: Python :: 3.8
Classifier: Programming Language :: Python :: 3.9
Classifier: Programming Language :: Python :: 3.10
Classifier: Programming Language :: Python :: 3.11
Classifier: Programming Language :: Python :: 3.12
Requires-Python: >=3.8, <4
License-File: LICENSE
Requires-Dist: eth-utils>=2
Requires-Dist: eth-typing>=3
Provides-Extra: coincurve
Requires-Dist: coincurve>=12.0.0; extra == "coincurve"
Provides-Extra: dev
Requires-Dist: coincurve>=12.0.0; extra == "dev"
Requires-Dist: build>=0.9.0; extra == "dev"
Requires-Dist: bumpversion>=0.5.3; extra == "dev"
Requires-Dist: ipython; extra == "dev"
Requires-Dist: pre-commit>=3.4.0; extra == "dev"
Requires-Dist: tox>=4.0.0; extra == "dev"
Requires-Dist: twine; extra == "dev"
Requires-Dist: wheel; extra == "dev"
Requires-Dist: towncrier<22,>=21; extra == "dev"
Requires-Dist: pytest>=7.0.0; extra == "dev"
Requires-Dist: asn1tools>=0.146.2; extra == "dev"
Requires-Dist: factory-boy>=3.0.1; extra == "dev"
Requires-Dist: pyasn1>=0.4.5; extra == "dev"
Requires-Dist: hypothesis>=5.10.3; extra == "dev"
Requires-Dist: eth-hash[pysha3]; extra == "dev"
Provides-Extra: docs
Requires-Dist: towncrier<22,>=21; extra == "docs"
Provides-Extra: test
Requires-Dist: pytest>=7.0.0; extra == "test"
Requires-Dist: asn1tools>=0.146.2; extra == "test"
Requires-Dist: factory-boy>=3.0.1; extra == "test"
Requires-Dist: pyasn1>=0.4.5; extra == "test"
Requires-Dist: hypothesis>=5.10.3; extra == "test"
Requires-Dist: eth-hash[pysha3]; extra == "test"
